caliendo/__init__.py
caliendo/call_descriptor.py
caliendo/config.py
caliendo/counter.py
caliendo/expected_value.py
caliendo/facade.py
caliendo/hooks.py
caliendo/logger.py
caliendo/patch.py
caliendo/pickling.py
caliendo/prompt.py
caliendo/util.py
caliendo/db/__init__.py
caliendo/db/flatfiles.py
caliendo-2.1.8.dist-info/DESCRIPTION.rst
caliendo-2.1.8.dist-info/METADATA
caliendo-2.1.8.dist-info/metadata.json
caliendo-2.1.8.dist-info/RECORD
caliendo-2.1.8.dist-info/top_level.txt
caliendo-2.1.8.dist-info/WHEEL
test/__init__.py
test/all_tests.py
test/caliendo_test.py
test/expected_value.py
test/foobar.py
test/test_patch.py
test/test_replay.py
test/test_with_nose.py
test/api/__init__.py
test/api/callback.py
test/api/foobar.py
test/api/foobarfoobaz.py
test/api/foobarfoobiz.py
test/api/foobaz.py
test/api/foobiz.py
test/api/myclass.py
test/api/services/__init__.py
test/api/services/bar.py
test/api/services/baz.py
test/api/services/biz.py
test/api/services/foo.py
test/nested/__init__.py
test/nested/bazbiz.py
